CHANGELOG.rst
CONTRIBUTORS.txt
LICENSE.txt
MANIFEST.in
README.rst
setup.py
django_mongonaut.egg-info/PKG-INFO
django_mongonaut.egg-info/SOURCES.txt
django_mongonaut.egg-info/dependency_links.txt
django_mongonaut.egg-info/not-zip-safe
django_mongonaut.egg-info/requires.txt
django_mongonaut.egg-info/top_level.txt
docs/Makefile
docs/api.rst
docs/conf.py
docs/configuration.rst
docs/future_usage.rst
docs/index.rst
docs/installation.rst
docs/make.bat
examples/blog/__init__.py
examples/blog/manage.py
examples/blog/settings.py
examples/blog/testrunner.py
examples/blog/urls.py
examples/blog/articles/__init__.py
examples/blog/articles/models.py
examples/blog/articles/mongoadmin.py
examples/blog/articles/urls.py
examples/blog/articles/views.py
examples/blog/articles/tests/__init__.py
examples/blog/articles/tests/test_models.py
mongonaut/__init__.py
mongonaut/exceptions.py
mongonaut/mixins.py
mongonaut/models.py
mongonaut/sites.py
mongonaut/urls.py
mongonaut/utils.py
mongonaut/views.py
mongonaut/forms/__init__.py
mongonaut/forms/form_mixins.py
mongonaut/forms/form_utils.py
mongonaut/forms/forms.py
mongonaut/forms/widgets.py
mongonaut/templates/mongonaut/base.html
mongonaut/templates/mongonaut/document_add_form.html
mongonaut/templates/mongonaut/document_delete.html
mongonaut/templates/mongonaut/document_detail.html
mongonaut/templates/mongonaut/document_edit_form.html
mongonaut/templates/mongonaut/document_list.html
mongonaut/templates/mongonaut/embedded_document_detail.html
mongonaut/templates/mongonaut/index.html
mongonaut/templates/mongonaut/actions/action_buttons.html
mongonaut/templates/mongonaut/includes/_delete_warning.html
mongonaut/templates/mongonaut/includes/_field.html
mongonaut/templates/mongonaut/includes/form.html
mongonaut/templates/mongonaut/includes/list_add.js
mongonaut/templatetags/__init__.py
mongonaut/templatetags/mongonaut_tags.py
tests/__init__.py
tests/runtests.py
tests/sites_tests.py
tests/view_tests.py
tests/common/__init__.py
tests/common/utils.py