Metadata-Version: 1.0
Name: django-mongonaut
Version: 0.2.20
Summary: An introspective interface for Django and MongoDB
Home-page: http://github.com/pydanny/django-mongonaut
Author: Daniel Greenfeld
Author-email: pydanny@gmail.com
License: MIT
Keywords: mongodb,django
Platform: UNKNOWN
Classifier: Development Status :: 4 - Beta
Classifier: Environment :: Web Environment
Classifier: Framework :: Django
Classifier: License :: OSI Approved :: BSD License
Classifier: Operating System :: OS Independent
Classifier: Programming Language :: JavaScript
Classifier: Programming Language :: Python :: 2.6
Classifier: Programming Language :: Python :: 2.7
Classifier: Programming Language :: Python :: 3.3
Classifier: Topic :: Internet :: WWW/HTTP
Classifier: Topic :: Internet :: WWW/HTTP :: Dynamic Content
Classifier: Topic :: Software Development :: Libraries :: Python Modules
